setup.py
kestrel/__init__.py
kestrel/client.py
pykestrel.egg-info/PKG-INFO
pykestrel.egg-info/SOURCES.txt
pykestrel.egg-info/dependency_links.txt
pykestrel.egg-info/requires.txt
pykestrel.egg-info/top_level.txt
pykestrel.egg-info/zip-safe