Metadata-Version: 1.0
Name: pykestrel
Version: 0.5.0
Summary: A python kestrel client
Home-page: https://github.com/matterkkila/pykestrel
Author: Matt Erkkila
Author-email: matt@matterkkila.com
License: BSD
Download-URL: https://github.com/matterkkila/pykestrel/tarball/0.5.0
Keywords: queues kestrel memcached
Platform: UNKNOWN
Classifier: Development Status :: 3 - Alpha
Classifier: Intended Audience :: Developers
Classifier: Intended Audience :: System Administrators
Classifier: Programming Language :: Python
